aiostaticmap/__init__.py
aiostaticmap/__main__.py
aiostaticmap/aiostaticmap.py
aiostaticmap-0.1.0.dist-info/LICENSE.txt
aiostaticmap-0.1.0.dist-info/METADATA
aiostaticmap-0.1.0.dist-info/WHEEL
aiostaticmap-0.1.0.dist-info/top_level.txt
aiostaticmap-0.1.0.dist-info/RECORD
