Metadata-Version: 2.1
Name: aiostaticmap
Version: 0.1.0
Summary: A small, python-based library for creating map images with lines and markers.
Home-page: https://github.com/mon4ter/aiostaticmap
Author: Christoph Lingg, Dmitry Galkin
Author-email: christoph@komoot.de, mon4ter@gmail.com
License: Apache License 2.0
Keywords: static map image osm aio async asyncio
Platform: UNKNOWN
Classifier: Development Status :: 4 - Beta
Classifier: Programming Language :: Python :: 3.5
Classifier: Programming Language :: Python :: 3.6
Classifier: Programming Language :: Python :: 3.7
Classifier: Programming Language :: Python :: 3.8
Classifier: Programming Language :: Python :: 3.9
Classifier: Programming Language :: Python :: 3.10
Classifier: License :: OSI Approved :: Apache Software License
Classifier: Operating System :: OS Independent
Requires-Dist: Pillow (<8.0,>=7.0)
Requires-Dist: aiohttp (<4.0,>=3.0)
